hatch_cythonize/__about__.py
hatch_cythonize/__init__.py
hatch_cythonize/constants.py
hatch_cythonize/devel.py
hatch_cythonize/hooks.py
hatch_cythonize/plugin.py
hatch_cythonize/temp.py
hatch_cythonize/types.py
hatch_cythonize/utils.py
hatch_cythonize/config/__init__.py
hatch_cythonize/config/autoimport.py
hatch_cythonize/config/config.py
hatch_cythonize/config/defaults.py
hatch_cythonize/config/files.py
hatch_cythonize/config/flags.py
hatch_cythonize/config/includes.py
hatch_cythonize/config/macros.py
hatch_cythonize/config/platform.py
hatch_cythonize/config/templates.py
hatch_cythonize-0.7.0.dist-info/METADATA
hatch_cythonize-0.7.0.dist-info/WHEEL
hatch_cythonize-0.7.0.dist-info/entry_points.txt
hatch_cythonize-0.7.0.dist-info/licenses/LICENSE.txt
hatch_cythonize-0.7.0.dist-info/RECORD
